seetm/__init__.py
seetm/__main__.py
seetm/seetm.py
seetm/cli/__init__.py
seetm/cli/seetm_cli.py
seetm/core/__init__.py
seetm/core/evaluator.py
seetm/core/extractor.py
seetm/core/test_core.py
seetm/core/token_mapper.py
seetm/core/word2vec.py
seetm/core/mappers/__init__.py
seetm/core/mappers/english_to_phonetics_mapper.py
seetm/core/mappers/ipa_to_sinhala_mapper.py
seetm/core/mappers/phonetics_to_sinhala_mapper.py
seetm/core/mappers/token_to_token_mapper.py
seetm/core/maps/__init__.py
seetm/core/maps/ipa_to_sinhala_maps.py
seetm/core/maps/phonetics_to_sinhala_maps.py
seetm/core/metrics/__init__.py
seetm/core/metrics/levenshtien.py
seetm/core/metrics/sequence_matcher.py
seetm/server/__init__.py
seetm/server/seetm_server.py
seetm/server/frontend/asset-manifest.json
seetm/server/frontend/index.html
seetm/server/frontend/manifest.json
seetm/server/frontend/res/scripts/bootstrap.min.js
seetm/server/frontend/res/scripts/jquery-3.6.0.min.js
seetm/server/frontend/res/styles/app_styles.css
seetm/server/frontend/res/styles/bootstrap.min.css
seetm/server/frontend/res/styles/ghost.css
seetm/server/frontend/static/css/main.49694fa9.css
seetm/server/frontend/static/css/main.49694fa9.css.map
seetm/server/frontend/static/js/main.e5f55161.js
seetm/server/frontend/static/js/main.e5f55161.js.LICENSE.txt
seetm/server/frontend/static/js/main.e5f55161.js.map
seetm/server/frontend/static/media/seetm.3f1cf4500e5eebfae1f7.png
seetm/server/frontend/static/media/seetm_light.6298431bf2e0ea36f181.png
seetm/server/seetm_api/__init__.py
seetm/server/seetm_api/routes.py
seetm/server/seetm_api/utils/__init__.py
seetm/server/seetm_api/utils/server_configs.py
seetm/shared/__init__.py
seetm/shared/constants.py
seetm/shared/evaluation.py
seetm/shared/exportable.py
seetm/shared/exceptions/__init__.py
seetm/shared/exceptions/base.py
seetm/shared/exceptions/cli.py
seetm/shared/exceptions/config.py
seetm/shared/exceptions/core.py
seetm/shared/exceptions/io.py
seetm/shared/exceptions/server.py
seetm-1.1.1.dist-info/LICENSE
seetm-1.1.1.dist-info/METADATA
seetm-1.1.1.dist-info/WHEEL
seetm-1.1.1.dist-info/entry_points.txt
seetm-1.1.1.dist-info/top_level.txt
seetm-1.1.1.dist-info/RECORD
